{
	"backtrace" : 0,
	"backtraceGraph" : 
	{
		"commands" : [],
		"files" : 
		[
			"Part2/2-16/CMakeLists.txt"
		],
		"nodes" : 
		[
			{
				"file" : 0
			}
		]
	},
	"dependencies" : 
	[
		{
			"id" : "2-16_autogen_timestamp_deps::@e8bd64d4cbc49c5fe9c7"
		}
	],
	"id" : "2-16_autogen::@e8bd64d4cbc49c5fe9c7",
	"isGeneratorProvided" : true,
	"name" : "2-16_autogen",
	"paths" : 
	{
		"build" : "Part2/2-16",
		"source" : "Part2/2-16"
	},
	"sourceGroups" : 
	[
		{
			"name" : "",
			"sourceIndexes" : 
			[
				0
			]
		},
		{
			"name" : "CMake Rules",
			"sourceIndexes" : 
			[
				1,
				2
			]
		}
	],
	"sources" : 
	[
		{
			"backtrace" : 0,
			"isGenerated" : true,
			"path" : "cmake-build-debug/Part2/2-16/CMakeFiles/2-16_autogen",
			"sourceGroupIndex" : 0
		},
		{
			"backtrace" : 0,
			"isGenerated" : true,
			"path" : "cmake-build-debug/Part2/2-16/CMakeFiles/2-16_autogen.rule",
			"sourceGroupIndex" : 1
		},
		{
			"backtrace" : 0,
			"isGenerated" : true,
			"path" : "cmake-build-debug/Part2/2-16/2-16_autogen/timestamp.rule",
			"sourceGroupIndex" : 1
		}
	],
	"type" : "UTILITY"
}
